psychro/__init__.py
psychro/lib.py
psychro/src/Prefix.py
psychro/src/Pressure.py
psychro/src/Temperature.py
psychro/src/Unit.py
psychro/src/psychro_functions.py
psychro-1.0.0.data/data/LICENSE
psychro-1.0.0.dist-info/LICENSE
psychro-1.0.0.dist-info/METADATA
psychro-1.0.0.dist-info/WHEEL
psychro-1.0.0.dist-info/top_level.txt
psychro-1.0.0.dist-info/zip-safe
psychro-1.0.0.dist-info/RECORD
