Metadata-Version: 2.1
Name: psychro
Version: 1.0.0
Summary: This engineering package deals with the physical and thermodynamic   properties of the air-water system very accurately. It can calculate all the   psychrometric data like dewpoint, wet bulb temperature, humid enthalpy,   moisture content, humid volume, vapor density etc.
Home-page: https://github.com/aminul71bd/psychro
Author: A K M Aminul Islam
Author-email: aminul71bd@gmail.com
Maintainer: A K M Aminul Islam
Maintainer-email: aminul71bd@gmail.com
License: NEWTONIA FREEWARE LICENSE
License-File: LICENSE
